README.md
setup.py
drbot/__init__.py
drbot/__main__.py
drbot/botbuilder.py
drbot/exceptions.py
drbot.egg-info/PKG-INFO
drbot.egg-info/SOURCES.txt
drbot.egg-info/dependency_links.txt
drbot.egg-info/requires.txt
drbot.egg-info/top_level.txt