Metadata-Version: 2.1
Name: drbot
Version: 1.0
Summary: A Python3 library for easily building devRant bots
Home-page: https://github.com/Ewpratten/drbot
Author: Evan Pratten
Author-email: ewpratten@gmail.com
License: UNKNOWN
Platform: UNKNOWN
Classifier: Programming Language :: Python :: 3
Classifier: Operating System :: OS Independent
Classifier: Development Status :: 5 - Production/Stable
